{"fields":[{"id":"PVTF_lAHOEGRxEM4BYPQyzhTWgck","name":"Title","type":"ProjectV2Field"},{"id":"PVTF_lAHOEGRxEM4BYPQyzhTWgco","name":"Assignees","type":"ProjectV2Field"},{"id":"PVTSSF_lAHOEGRxEM4BYPQyzhTWgcs","name":"Status","options":[{"id":"f75ad846","name":"Todo"},{"id":"47fc9ee4","name":"In Progress"},{"id":"98236657","name":"Done"}],"type":"ProjectV2SingleSelectField"},{"id":"PVTF_lAHOEGRxEM4BYPQyzhTWgcw","name":"Labels","type":"ProjectV2Field"},{"id":"PVTF_lAHOEGRxEM4BYPQyzhTWgc0","name":"Linked pull requests","type":"ProjectV2Field"},{"id":"PVTF_lAHOEGRxEM4BYPQyzhTWgc4","name":"Milestone","type":"ProjectV2Field"},{"id":"PVTF_lAHOEGRxEM4BYPQyzhTWgc8","name":"Repository","type":"ProjectV2Field"},{"id":"PVTF_lAHOEGRxEM4BYPQyzhTWgdA","name":"Reviewers","type":"ProjectV2Field"},{"id":"PVTF_lAHOEGRxEM4BYPQyzhTWgdE","name":"Parent issue","type":"ProjectV2Field"},{"id":"PVTF_lAHOEGRxEM4BYPQyzhTWgdI","name":"Sub-issues progress","type":"ProjectV2Field"},{"id":"PVTF_lAHOEGRxEM4BYPQyzhTWgdM","name":"Created","type":"ProjectV2Field"},{"id":"PVTF_lAHOEGRxEM4BYPQyzhTWgdQ","name":"Updated","type":"ProjectV2Field"},{"id":"PVTF_lAHOEGRxEM4BYPQyzhTWgdU","name":"Closed","type":"ProjectV2Field"},{"id":"PVTSSF_lAHOEGRxEM4BYPQyzhTWulI","name":"Project","options":[{"id":"9ab41bcb","name":"Project_Command_Center"},{"id":"3b8dd9d0","name":"CityBrain"},{"id":"3cc00480","name":"SkyEdge"},{"id":"cc18bacb","name":"BioDockLab"},{"id":"f4c2c1a4","name":"UAM Radio Ops"},{"id":"5207e8e7","name":"FieldOps"},{"id":"5d483b3b","name":"Satellite GCS"},{"id":"4445dcf6","name":"Other"}],"type":"ProjectV2SingleSelectField"},{"id":"PVTF_lAHOEGRxEM4BYPQyzhTWulM","name":"Sub Project","type":"ProjectV2Field"},{"id":"PVTSSF_lAHOEGRxEM4BYPQyzhTWumE","name":"Department","options":[{"id":"29c5b814","name":"컴퓨터공학"},{"id":"5bf3cbc4","name":"AI"},{"id":"074468e4","name":"게임공학"},{"id":"2f4ebec2","name":"생명공학"},{"id":"1090a2a6","name":"항공드론"},{"id":"e10c3ae4","name":"경영"},{"id":"681a659f","name":"디자인"},{"id":"1c5f6484","name":"기타"}],"type":"ProjectV2SingleSelectField"},{"id":"PVTSSF_lAHOEGRxEM4BYPQyzhTWum8","name":"Role","options":[{"id":"ee29db61","name":"PM"},{"id":"c1a46b21","name":"Backend"},{"id":"142359dc","name":"Frontend"},{"id":"3c31ed00","name":"Mobile"},{"id":"a288483c","name":"Data"},{"id":"7341cd08","name":"DevOps / GitHub Ops"},{"id":"840565dc","name":"Hardware / Embedded"},{"id":"537e4276","name":"Research / Documentation"},{"id":"b5d8c34f","name":"Design / UX"},{"id":"0798b13d","name":"Business / Operations"},{"id":"aa700d0c","name":"Other"}],"type":"ProjectV2SingleSelectField"},{"id":"PVTF_lAHOEGRxEM4BYPQyzhTWun0","name":"Skill Track","type":"ProjectV2Field"},{"id":"PVTSSF_lAHOEGRxEM4BYPQyzhTWun4","name":"Priority","options":[{"id":"320ffeed","name":"P0 - Critical"},{"id":"6a9ad1b6","name":"P1 - High"},{"id":"7f42413e","name":"P2 - Normal"},{"id":"dbbdb4bc","name":"P3 - Low"}],"type":"ProjectV2SingleSelectField"},{"id":"PVTF_lAHOEGRxEM4BYPQyzhTWun8","name":"Start Date","type":"ProjectV2Field"},{"id":"PVTF_lAHOEGRxEM4BYPQyzhTWuoA","name":"Target Date","type":"ProjectV2Field"},{"id":"PVTF_lAHOEGRxEM4BYPQyzhTWuqA","name":"Progress %","type":"ProjectV2Field"},{"id":"PVTF_lAHOEGRxEM4BYPQyzhTWurM","name":"Related Repository","type":"ProjectV2Field"},{"id":"PVTF_lAHOEGRxEM4BYPQyzhTWus8","name":"Related Issue","type":"ProjectV2Field"},{"id":"PVTF_lAHOEGRxEM4BYPQyzhTWutA","name":"Evidence / Output","type":"ProjectV2Field"},{"id":"PVTF_lAHOEGRxEM4BYPQyzhTWutE","name":"Blocker","type":"ProjectV2Field"},{"id":"PVTF_lAHOEGRxEM4BYPQyzhTWuuU","name":"Next Action","type":"ProjectV2Field"}],"totalCount":27}
